<?xml version="1.0" encoding="utf-8"?><Produits><IdProduit>700231034</IdProduit><Titre>Tee-shirt manches volantées motifs fantaisie fille</Titre><Description>&lt;div class="description-block description-block--intro"&gt;
&lt;p class="description-text"&gt;Des froufrous ou des sequins ? Ce &lt;strong&gt;T-shirt&lt;/strong&gt;  a le pouvoir de rendre les filles craquantes. Un motif romantique ou bohème animé de détails fantaisie, des manches soulignées de volants charmants... et le tour est joué !&lt;/p&gt;
&lt;ul class="description-list"&gt;
&lt;li&gt;&lt;strong&gt;T-shirt fille manches volantées&lt;/strong&gt;&lt;/li&gt;
&lt;li&gt;Encolure ronde&lt;/li&gt;
&lt;li&gt;Motif devant fleurs en relief et pompons ou sequins,selon coloris, détails irisés&lt;/li&gt;
&lt;li&gt;Volants fantaisie aux épaules&lt;/li&gt;
&lt;li&gt;Manches longues&lt;/li&gt;
&lt;/ul&gt;
&lt;/div&gt;
&lt;p class="description-text"&gt;&lt;strong&gt;Tee-shirt fille &lt;/strong&gt;en pur coton.&lt;/p&gt;</Description><PrixAppel><Devise1>8.99€</Devise1></PrixAppel><CodeMarque>VB</CodeMarque><TauxDemarque>40</TauxDemarque><DisponibiliteLibelle>Disponible</DisponibiliteLibelle><ImageProduit /><Colors><Color><Code>6350</Code><Libelle>ivoire</Libelle><Images><Zoom>https://media.vertbaudet.fr/Pictures/vertbaudet/155173/tee-shirt-manches-volantees-motifs-fantaisie-fille.jpg</Zoom><Grande>https://media.vertbaudet.fr/Pictures/vertbaudet/155173/tee-shirt-manches-volantees-motifs-fantaisie-fille.jpg?width=542</Grande><Moyenne>https://media.vertbaudet.fr/Pictures/vertbaudet/155173/tee-shirt-manches-volantees-motifs-fantaisie-fille.jpg?width=285</Moyenne><Petite>https://media.vertbaudet.fr/Pictures/vertbaudet/155173/tee-shirt-manches-volantees-motifs-fantaisie-fille.jpg?width=132</Petite><TresPetite>https://media.vertbaudet.fr/Pictures/vertbaudet/155173/tee-shirt-manches-volantees-motifs-fantaisie-fille.jpg?width=59</TresPetite></Images><ColorPreviewUrl>https://media.vertbaudet.fr/Pictures/vertbaudet/155100/tee-shirt-manches-volantees-motifs-fantaisie-fille.jpg?width=21</ColorPreviewUrl></Color><Color><Code>6630</Code><Libelle>rose fumé</Libelle><Images><Zoom>https://media.vertbaudet.fr/Pictures/vertbaudet/155526/tee-shirt-manches-volantees-motifs-fantaisie-fille.jpg</Zoom><Grande>https://media.vertbaudet.fr/Pictures/vertbaudet/155526/tee-shirt-manches-volantees-motifs-fantaisie-fille.jpg?width=542</Grande><Moyenne>https://media.vertbaudet.fr/Pictures/vertbaudet/155526/tee-shirt-manches-volantees-motifs-fantaisie-fille.jpg?width=285</Moyenne><Petite>https://media.vertbaudet.fr/Pictures/vertbaudet/155526/tee-shirt-manches-volantees-motifs-fantaisie-fille.jpg?width=132</Petite><TresPetite>https://media.vertbaudet.fr/Pictures/vertbaudet/155526/tee-shirt-manches-volantees-motifs-fantaisie-fille.jpg?width=59</TresPetite></Images><ColorPreviewUrl>https://media.vertbaudet.fr/Pictures/vertbaudet/155276/tee-shirt-manches-volantees-motifs-fantaisie-fille.jpg?width=21</ColorPreviewUrl></Color></Colors><Domaine><Securise>https://www.vertbaudet.fr</Securise><Normal>http://www.vertbaudet.fr</Normal></Domaine><Variants><Variant><Reference>6414271</Reference><Disponibilite>Disponible</Disponibilite><DisponibiliteLibelle>Disponible</DisponibiliteLibelle><DateLivraisonDiffere /><Prix><Devise1>8.99€</Devise1></Prix><PrixBarre><Devise1>14.99€</Devise1></PrixBarre><Taille><TailleLibelle>2A</TailleLibelle><TaillePres>002</TaillePres></Taille><Coloris>ivoire</Coloris><CodeColoris>6350</CodeColoris><PICTOLG>ope-rentree-kids-ah21-picto.svg</PICTOLG><PICTOPD>ope-rentree-kids-ah21-picto.svg</PICTOPD><TauxDemarque>40</TauxDemarque><TauxDemarqueClub>0</TauxDemarqueClub><MontantDemarqueClub>0</MontantDemarqueClub><CampaignType>None</CampaignType><IsCustomizable>false</IsCustomizable></Variant><Variant><Reference>6414271</Reference><Disponibilite>Disponible</Disponibilite><DisponibiliteLibelle>Disponible</DisponibiliteLibelle><DateLivraisonDiffere /><Prix><Devise1>8.99€</Devise1></Prix><PrixBarre><Devise1>14.99€</Devise1></PrixBarre><Taille><TailleLibelle>3A</TailleLibelle><TaillePres>003</TaillePres></Taille><Coloris>ivoire</Coloris><CodeColoris>6350</CodeColoris><PICTOLG>ope-rentree-kids-ah21-picto.svg</PICTOLG><PICTOPD>ope-rentree-kids-ah21-picto.svg</PICTOPD><TauxDemarque>40</TauxDemarque><TauxDemarqueClub>0</TauxDemarqueClub><MontantDemarqueClub>0</MontantDemarqueClub><CampaignType>None</CampaignType><IsCustomizable>false</IsCustomizable></Variant><Variant><Reference>6414271</Reference><Disponibilite>Disponible</Disponibilite><DisponibiliteLibelle>Disponible</DisponibiliteLibelle><DateLivraisonDiffere /><Prix><Devise1>8.99€</Devise1></Prix><PrixBarre><Devise1>14.99€</Devise1></PrixBarre><Taille><TailleLibelle>4A</TailleLibelle><TaillePres>004</TaillePres></Taille><Coloris>ivoire</Coloris><CodeColoris>6350</CodeColoris><PICTOLG>ope-rentree-kids-ah21-picto.svg</PICTOLG><PICTOPD>ope-rentree-kids-ah21-picto.svg</PICTOPD><TauxDemarque>40</TauxDemarque><TauxDemarqueClub>0</TauxDemarqueClub><MontantDemarqueClub>0</MontantDemarqueClub><CampaignType>None</CampaignType><IsCustomizable>false</IsCustomizable></Variant><Variant><Reference>6414271</Reference><Disponibilite>Disponible</Disponibilite><DisponibiliteLibelle>Disponible</DisponibiliteLibelle><DateLivraisonDiffere /><Prix><Devise1>8.99€</Devise1></Prix><PrixBarre><Devise1>14.99€</Devise1></PrixBarre><Taille><TailleLibelle>5A</TailleLibelle><TaillePres>005</TaillePres></Taille><Coloris>ivoire</Coloris><CodeColoris>6350</CodeColoris><PICTOLG>ope-rentree-kids-ah21-picto.svg</PICTOLG><PICTOPD>ope-rentree-kids-ah21-picto.svg</PICTOPD><TauxDemarque>40</TauxDemarque><TauxDemarqueClub>0</TauxDemarqueClub><MontantDemarqueClub>0</MontantDemarqueClub><CampaignType>None</CampaignType><IsCustomizable>false</IsCustomizable></Variant><Variant><Reference>6414271</Reference><Disponibilite>Disponible</Disponibilite><DisponibiliteLibelle>Disponible</DisponibiliteLibelle><DateLivraisonDiffere /><Prix><Devise1>8.99€</Devise1></Prix><PrixBarre><Devise1>14.99€</Devise1></PrixBarre><Taille><TailleLibelle>6A</TailleLibelle><TaillePres>006</TaillePres></Taille><Coloris>ivoire</Coloris><CodeColoris>6350</CodeColoris><PICTOLG>ope-rentree-kids-ah21-picto.svg</PICTOLG><PICTOPD>ope-rentree-kids-ah21-picto.svg</PICTOPD><TauxDemarque>40</TauxDemarque><TauxDemarqueClub>0</TauxDemarqueClub><MontantDemarqueClub>0</MontantDemarqueClub><CampaignType>None</CampaignType><IsCustomizable>false</IsCustomizable></Variant><Variant><Reference>6414271</Reference><Disponibilite>Disponible</Disponibilite><DisponibiliteLibelle>Disponible</DisponibiliteLibelle><DateLivraisonDiffere /><Prix><Devise1>8.99€</Devise1></Prix><PrixBarre><Devise1>14.99€</Devise1></PrixBarre><Taille><TailleLibelle>8A</TailleLibelle><TaillePres>008</TaillePres></Taille><Coloris>ivoire</Coloris><CodeColoris>6350</CodeColoris><PICTOLG>ope-rentree-kids-ah21-picto.svg</PICTOLG><PICTOPD>ope-rentree-kids-ah21-picto.svg</PICTOPD><TauxDemarque>40</TauxDemarque><TauxDemarqueClub>0</TauxDemarqueClub><MontantDemarqueClub>0</MontantDemarqueClub><CampaignType>None</CampaignType><IsCustomizable>false</IsCustomizable></Variant><Variant><Reference>6414271</Reference><Disponibilite>Disponible</Disponibilite><DisponibiliteLibelle>Disponible</DisponibiliteLibelle><DateLivraisonDiffere /><Prix><Devise1>8.99€</Devise1></Prix><PrixBarre><Devise1>14.99€</Devise1></PrixBarre><Taille><TailleLibelle>10A</TailleLibelle><TaillePres>010</TaillePres></Taille><Coloris>ivoire</Coloris><CodeColoris>6350</CodeColoris><PICTOLG>ope-rentree-kids-ah21-picto.svg</PICTOLG><PICTOPD>ope-rentree-kids-ah21-picto.svg</PICTOPD><TauxDemarque>40</TauxDemarque><TauxDemarqueClub>0</TauxDemarqueClub><MontantDemarqueClub>0</MontantDemarqueClub><CampaignType>None</CampaignType><IsCustomizable>false</IsCustomizable></Variant><Variant><Reference>6414271</Reference><Disponibilite>Disponible</Disponibilite><DisponibiliteLibelle>Disponible</DisponibiliteLibelle><DateLivraisonDiffere /><Prix><Devise1>8.99€</Devise1></Prix><PrixBarre><Devise1>14.99€</Devise1></PrixBarre><Taille><TailleLibelle>12A</TailleLibelle><TaillePres>012</TaillePres></Taille><Coloris>ivoire</Coloris><CodeColoris>6350</CodeColoris><PICTOLG>ope-rentree-kids-ah21-picto.svg</PICTOLG><PICTOPD>ope-rentree-kids-ah21-picto.svg</PICTOPD><TauxDemarque>40</TauxDemarque><TauxDemarqueClub>0</TauxDemarqueClub><MontantDemarqueClub>0</MontantDemarqueClub><CampaignType>None</CampaignType><IsCustomizable>false</IsCustomizable></Variant><Variant><Reference>6414271</Reference><Disponibilite>Disponible</Disponibilite><DisponibiliteLibelle>Disponible</DisponibiliteLibelle><DateLivraisonDiffere /><Prix><Devise1>8.99€</Devise1></Prix><PrixBarre><Devise1>14.99€</Devise1></PrixBarre><Taille><TailleLibelle>14A</TailleLibelle><TaillePres>014</TaillePres></Taille><Coloris>ivoire</Coloris><CodeColoris>6350</CodeColoris><PICTOLG>ope-rentree-kids-ah21-picto.svg</PICTOLG><PICTOPD>ope-rentree-kids-ah21-picto.svg</PICTOPD><TauxDemarque>40</TauxDemarque><TauxDemarqueClub>0</TauxDemarqueClub><MontantDemarqueClub>0</MontantDemarqueClub><CampaignType>None</CampaignType><IsCustomizable>false</IsCustomizable></Variant><Variant><Reference>6414280</Reference><Disponibilite>Disponible</Disponibilite><DisponibiliteLibelle>Disponible</DisponibiliteLibelle><DateLivraisonDiffere /><Prix><Devise1>8.99€</Devise1></Prix><PrixBarre><Devise1>14.99€</Devise1></PrixBarre><Taille><TailleLibelle>2A</TailleLibelle><TaillePres>002</TaillePres></Taille><Coloris>rose fumé</Coloris><CodeColoris>6630</CodeColoris><PICTOLG>ope-rentree-kids-ah21-picto.svg</PICTOLG><PICTOPD>ope-rentree-kids-ah21-picto.svg</PICTOPD><TauxDemarque>40</TauxDemarque><TauxDemarqueClub>0</TauxDemarqueClub><MontantDemarqueClub>0</MontantDemarqueClub><CampaignType>None</CampaignType><IsCustomizable>false</IsCustomizable></Variant><Variant><Reference>6414280</Reference><Disponibilite>Disponible</Disponibilite><DisponibiliteLibelle>Disponible</DisponibiliteLibelle><DateLivraisonDiffere /><Prix><Devise1>8.99€</Devise1></Prix><PrixBarre><Devise1>14.99€</Devise1></PrixBarre><Taille><TailleLibelle>3A</TailleLibelle><TaillePres>003</TaillePres></Taille><Coloris>rose fumé</Coloris><CodeColoris>6630</CodeColoris><PICTOLG>ope-rentree-kids-ah21-picto.svg</PICTOLG><PICTOPD>ope-rentree-kids-ah21-picto.svg</PICTOPD><TauxDemarque>40</TauxDemarque><TauxDemarqueClub>0</TauxDemarqueClub><MontantDemarqueClub>0</MontantDemarqueClub><CampaignType>None</CampaignType><IsCustomizable>false</IsCustomizable></Variant><Variant><Reference>6414280</Reference><Disponibilite>Disponible</Disponibilite><DisponibiliteLibelle>Disponible</DisponibiliteLibelle><DateLivraisonDiffere /><Prix><Devise1>8.99€</Devise1></Prix><PrixBarre><Devise1>14.99€</Devise1></PrixBarre><Taille><TailleLibelle>4A</TailleLibelle><TaillePres>004</TaillePres></Taille><Coloris>rose fumé</Coloris><CodeColoris>6630</CodeColoris><PICTOLG>ope-rentree-kids-ah21-picto.svg</PICTOLG><PICTOPD>ope-rentree-kids-ah21-picto.svg</PICTOPD><TauxDemarque>40</TauxDemarque><TauxDemarqueClub>0</TauxDemarqueClub><MontantDemarqueClub>0</MontantDemarqueClub><CampaignType>None</CampaignType><IsCustomizable>false</IsCustomizable></Variant><Variant><Reference>6414280</Reference><Disponibilite>Disponible</Disponibilite><DisponibiliteLibelle>Disponible</DisponibiliteLibelle><DateLivraisonDiffere /><Prix><Devise1>8.99€</Devise1></Prix><PrixBarre><Devise1>14.99€</Devise1></PrixBarre><Taille><TailleLibelle>5A</TailleLibelle><TaillePres>005</TaillePres></Taille><Coloris>rose fumé</Coloris><CodeColoris>6630</CodeColoris><PICTOLG>ope-rentree-kids-ah21-picto.svg</PICTOLG><PICTOPD>ope-rentree-kids-ah21-picto.svg</PICTOPD><TauxDemarque>40</TauxDemarque><TauxDemarqueClub>0</TauxDemarqueClub><MontantDemarqueClub>0</MontantDemarqueClub><CampaignType>None</CampaignType><IsCustomizable>false</IsCustomizable></Variant><Variant><Reference>6414280</Reference><Disponibilite>Disponible</Disponibilite><DisponibiliteLibelle>Disponible</DisponibiliteLibelle><DateLivraisonDiffere /><Prix><Devise1>8.99€</Devise1></Prix><PrixBarre><Devise1>14.99€</Devise1></PrixBarre><Taille><TailleLibelle>6A</TailleLibelle><TaillePres>006</TaillePres></Taille><Coloris>rose fumé</Coloris><CodeColoris>6630</CodeColoris><PICTOLG>ope-rentree-kids-ah21-picto.svg</PICTOLG><PICTOPD>ope-rentree-kids-ah21-picto.svg</PICTOPD><TauxDemarque>40</TauxDemarque><TauxDemarqueClub>0</TauxDemarqueClub><MontantDemarqueClub>0</MontantDemarqueClub><CampaignType>None</CampaignType><IsCustomizable>false</IsCustomizable></Variant><Variant><Reference>6414280</Reference><Disponibilite>Disponible</Disponibilite><DisponibiliteLibelle>Disponible</DisponibiliteLibelle><DateLivraisonDiffere /><Prix><Devise1>8.99€</Devise1></Prix><PrixBarre><Devise1>14.99€</Devise1></PrixBarre><Taille><TailleLibelle>8A</TailleLibelle><TaillePres>008</TaillePres></Taille><Coloris>rose fumé</Coloris><CodeColoris>6630</CodeColoris><PICTOLG>ope-rentree-kids-ah21-picto.svg</PICTOLG><PICTOPD>ope-rentree-kids-ah21-picto.svg</PICTOPD><TauxDemarque>40</TauxDemarque><TauxDemarqueClub>0</TauxDemarqueClub><MontantDemarqueClub>0</MontantDemarqueClub><CampaignType>None</CampaignType><IsCustomizable>false</IsCustomizable></Variant><Variant><Reference>6414280</Reference><Disponibilite>Disponible</Disponibilite><DisponibiliteLibelle>Disponible</DisponibiliteLibelle><DateLivraisonDiffere /><Prix><Devise1>8.99€</Devise1></Prix><PrixBarre><Devise1>14.99€</Devise1></PrixBarre><Taille><TailleLibelle>10A</TailleLibelle><TaillePres>010</TaillePres></Taille><Coloris>rose fumé</Coloris><CodeColoris>6630</CodeColoris><PICTOLG>ope-rentree-kids-ah21-picto.svg</PICTOLG><PICTOPD>ope-rentree-kids-ah21-picto.svg</PICTOPD><TauxDemarque>40</TauxDemarque><TauxDemarqueClub>0</TauxDemarqueClub><MontantDemarqueClub>0</MontantDemarqueClub><CampaignType>None</CampaignType><IsCustomizable>false</IsCustomizable></Variant><Variant><Reference>6414280</Reference><Disponibilite>Disponible</Disponibilite><DisponibiliteLibelle>Disponible</DisponibiliteLibelle><DateLivraisonDiffere /><Prix><Devise1>8.99€</Devise1></Prix><PrixBarre><Devise1>14.99€</Devise1></PrixBarre><Taille><TailleLibelle>12A</TailleLibelle><TaillePres>012</TaillePres></Taille><Coloris>rose fumé</Coloris><CodeColoris>6630</CodeColoris><PICTOLG>ope-rentree-kids-ah21-picto.svg</PICTOLG><PICTOPD>ope-rentree-kids-ah21-picto.svg</PICTOPD><TauxDemarque>40</TauxDemarque><TauxDemarqueClub>0</TauxDemarqueClub><MontantDemarqueClub>0</MontantDemarqueClub><CampaignType>None</CampaignType><IsCustomizable>false</IsCustomizable></Variant><Variant><Reference>6414280</Reference><Disponibilite>Disponible</Disponibilite><DisponibiliteLibelle>Disponible</DisponibiliteLibelle><DateLivraisonDiffere /><Prix><Devise1>8.99€</Devise1></Prix><PrixBarre><Devise1>14.99€</Devise1></PrixBarre><Taille><TailleLibelle>14A</TailleLibelle><TaillePres>014</TaillePres></Taille><Coloris>rose fumé</Coloris><CodeColoris>6630</CodeColoris><PICTOLG>ope-rentree-kids-ah21-picto.svg</PICTOLG><PICTOPD>ope-rentree-kids-ah21-picto.svg</PICTOPD><TauxDemarque>40</TauxDemarque><TauxDemarqueClub>0</TauxDemarqueClub><MontantDemarqueClub>0</MontantDemarqueClub><CampaignType>None</CampaignType><IsCustomizable>false</IsCustomizable></Variant></Variants><Url>http://www.vertbaudet.fr/ficheproduit.htm?ProductId=700231034</Url><IsCustomizable>false</IsCustomizable></Produits>